cigram/__init__.py
cigram/generators.py
cigram/cmodel/__init__.py
cigram/cmodel/cmodel.cc
cigram/cmodel/distributions.cc
cigram/cmodel/generate_graph.cc
cigram/cmodel/sample.cc
cigram/lfr_model/__init__.py
cigram/lfr_model/benchm.cpp
cigram/lfr_model/cast.cpp
cigram/lfr_model/cc.cpp
cigram/lfr_model/combinatorics.cpp
cigram/lfr_model/lfr_model.cc
cigram/lfr_model/random.cpp
cigram/network_opt/__init__.py
cigram/network_opt/cigram_optimiser.py
cigram/network_opt/fitness_measures.py
cigram/network_opt/model_parameters.py
cigram-0.1.1.dist-info/DESCRIPTION.rst
cigram-0.1.1.dist-info/METADATA
cigram-0.1.1.dist-info/RECORD
cigram-0.1.1.dist-info/WHEEL
cigram-0.1.1.dist-info/metadata.json
cigram-0.1.1.dist-info/top_level.txt
